kieran_mcp_upload_pypi/__init__.py
kieran_mcp_upload_pypi-0.1.0.dist-info/METADATA
kieran_mcp_upload_pypi-0.1.0.dist-info/WHEEL
kieran_mcp_upload_pypi-0.1.0.dist-info/entry_points.txt
kieran_mcp_upload_pypi-0.1.0.dist-info/RECORD
