Metadata-Version: 2.4
Name: kieran-mcp-upload-pypi
Version: 0.1.0
Summary: Add your description here
Author-email: bruan <1441584221@qq.com>
Requires-Python: >=3.13
Requires-Dist: mcp[cli]>=1.13.0
